interface/__init__.py
interface/cls_chat.py
interface/cls_few_shot_factory.py
interface/cls_groq_interface.py
interface/cls_ollama_client.py
interface/cls_web_scraper.py
language_model_toolkit-0.1.dist-info/METADATA
language_model_toolkit-0.1.dist-info/WHEEL
language_model_toolkit-0.1.dist-info/top_level.txt
language_model_toolkit-0.1.dist-info/RECORD
