Metadata-Version: 2.1
Name: language-model-toolkit
Version: 0.1
Summary: A holisitic for interfacing with ollama and other llm hosts. Created mainly for private experimentation.
Home-page: https://github.com/AutomatedAlchemy/Language-Model-Toolkit
Author: Steffen Probst
Author-email: probststeffen15@t-online.de
License: UNKNOWN
Platform: UNKNOWN
Requires-Dist: matplotlib (==3.7.2)
Requires-Dist: networkx (==3.1)
Requires-Dist: openai
Requires-Dist: python-dotenv
Requires-Dist: torch (==2.0.1)
Requires-Dist: transformers
Requires-Dist: websockets (==11.0.3)
